pygame_tutor-0.1.8.dist-info/licenses/LICENSE
pygametutor/__init__.py
pygametutor/main.py
pygametutor/core/__init__.py
pygametutor/core/base.py
pygametutor/core/code_viewer.py
pygametutor/core/loader.py
pygametutor/core/screen.py
pygametutor/lessons/__init__.py
pygametutor/lessons/lesson_00_about.py
pygametutor/lessons/lesson_01_comet.py
pygametutor/lessons/lesson_02_physics.py
pygametutor/lessons/lesson_03_input.py
pygametutor/lessons/lesson_04_breakout.py
pygametutor/lessons/lesson_05_arkanoid.py
pygametutor/lessons/img/ball.png
pygametutor/lessons/img/enemy.png
pygametutor/lessons/img/platform.png
pygametutor/settings/__init__.py
pygametutor/settings/constants.py
pygame_tutor-0.1.8.dist-info/METADATA
pygame_tutor-0.1.8.dist-info/WHEEL
pygame_tutor-0.1.8.dist-info/entry_points.txt
pygame_tutor-0.1.8.dist-info/top_level.txt
pygame_tutor-0.1.8.dist-info/RECORD
