Metadata-Version: 2.4
Name: pygame-tutor
Version: 0.1.8
Summary: Interactive educational platform for learning Pygame
Author-email: Sergey Samoylov <linews@yandex.ru>
License: GNU General Public License v3.0
Classifier: Development Status :: 4 - Beta
Classifier: Intended Audience :: Education
Classifier: License :: OSI Approved :: GNU General Public License v3 (GPLv3)
Classifier: Programming Language :: Python :: 3
Classifier: Operating System :: OS Independent
Requires-Python: >=3.8
License-File: LICENSE
Requires-Dist: pygame>=2.0.0
Dynamic: license-file
